Workbook

Sheet Comps_Val
B2: Amount in crores
B3: Comparable Company Valuation
D5: Market Data | K5: Financials | O5: Valuation
B6: Company | C6: Ticker | D6: Share Price | E6: Shares Outstanding | F6: Equity Val | G6: Net Debt | H6: Enterprise Value | K6: Revenue | L6: EBITDA | M6: Net Income | O6: EV/Revenue | P6: EV/EBITDA | Q6: P/E
B8: =Data!C5 -> Cipla | D8: =Data!D5 -> 893.35 | E8: =Data!E5 -> 80.72 | F8: =D8*E8 -> 72111.212 | G8: =Data!I5 -> -860.82 | H8: =F8+G8 -> 71250.392 | K8: =Data!K5 -> 22274.15 | L8: =Data!L5 -> 3786.61 | M8: =Data!M5 -> 2682.08 | O8: =$H8/K8 -> 3.1987929 | P8: =$H8/L8 -> 18.816406 | Q8: =F8/M8 -> 26.886302
B9: =Data!C3 -> Sun Pharma.Inds. | D9: =Data!D3 -> 1012.1 | E9: =Data!E3 -> 239.93 | F9: =D9*E9 -> 242833.15 | G9: =Data!I3 -> -667.82 | H9: =F9+G9 -> 242165.33 | K9: =Data!K3 -> 42401.77 | L9: =Data!L3 -> 9328.39 | M9: =Data!M3 -> 4302.66 | O9: =$H9/K9 -> 5.7112081 | P9: =$H9/L9 -> 25.960035 | Q9: =F9/M9 -> 56.437914
B10: =Data!C4 -> Dr Reddy's Labs | D10: =Data!D4 -> 4699.4 | E10: =Data!E4 -> 16.65 | F10: =D10*E10 -> 78245.01 | G10: =Data!I4 -> -690.3 | H10: =F10+G10 -> 77554.71 | K10: =Data!K4 -> 23829.5 | L10: =Data!L4 -> 5004.2 | M10: =Data!M4 -> 3644.1 | O10: =$H10/K10 -> 3.2545672 | P10: =$H10/L10 -> 15.497924 | Q10: =F10/M10 -> 21.471697
B11: =Data!C6 -> Torrent Pharma. | D11: =Data!D6 -> 1574.75 | E11: =Data!E6 -> 33.84 | F11: =D11*E11 -> 53289.54 | G11: =Data!I6 -> 3679.59 | H11: =F11+G11 -> 56969.13 | K11: =Data!K6 -> 9260 | L11: =Data!L6 -> 2129.8 | M11: =Data!M6 -> 831 | O11: =$H11/K11 -> 6.1521739 | P11: =$H11/L11 -> 26.748582 | Q11: =F11/M11 -> 64.127004
B12: =Data!C7 -> Zydus Lifesci. | D12: =Data!D7 -> 494.15 | E12: =Data!E7 -> 101.22 | F12: =D12*E12 -> 50017.863 | G12: =Data!I7 -> 1339.1 | H12: =F12+G12 -> 51356.963 | K12: =Data!K7 -> 16433.5 | L12: =Data!L7 -> 2793.7 | M12: =Data!M7 -> 2187 | O12: =$H12/K12 -> 3.1251385 | P12: =$H12/L12 -> 18.383135 | Q12: =F12/M12 -> 22.870536
B13: =Data!C8 -> Alkem Lab | D13: =Data!D8 -> 3405.65 | E13: =Data!E8 -> 11.96 | F13: =D13*E13 -> 40731.574 | G13: =Data!I8 -> -723.99 | H13: =F13+G13 -> 40007.584 | K13: =Data!K8 -> 11180.52 | L13: =Data!L8 -> 1453.47 | M13: =Data!M8 -> 1047.34 | O13: =$H13/K13 -> 3.5783295 | P13: =$H13/L13 -> 27.525566 | Q13: =F13/M13 -> 38.890498
B14: =Data!C9 -> Aurobindo Pharma | D14: =Data!D9 -> 535.1 | E14: =Data!E9 -> 58.59 | F14: =D14*E14 -> 31351.509 | G14: =Data!I9 -> 311.2 | H14: =F14+G14 -> 31662.709 | K14: =Data!K9 -> 24191.79 | L14: =Data!L9 -> 2661.1 | M14: =Data!M9 -> 1997.9 | O14: =$H14/K14 -> 1.3088204 | P14: =$H14/L14 -> 11.898354 | Q14: =F14/M14 -> 15.692231
B15: =Data!C10 -> Biocon | D15: =Data!D10 -> 215.8 | E15: =Data!E10 -> 120.06 | F15: =D15*E15 -> 25908.948 | G15: =Data!I10 -> 4111.9 | H15: =F15+G15 -> 30020.848 | K15: =Data!K10 -> 9809.1 | L15: =Data!L10 -> 1275.18 | M15: =Data!M10 -> 512.4 | O15: =$H15/K15 -> 3.0605099 | P15: =$H15/L15 -> 23.542439 | Q15: =F15/M15 -> 50.563911
B16: =Data!C11 -> Syngene Intl. | D16: =Data!D11 -> 604.65 | E16: =Data!E11 -> 40.14 | F16: =D16*E16 -> 24270.651 | G16: =Data!I11 -> 493.9 | H16: =F16+G16 -> 24764.551 | K16: =Data!K11 -> 2957.9 | L16: =Data!L11 -> 591.58 | M16: =Data!M11 -> 431.2 | O16: =$H16/K16 -> 8.3723422 | P16: =$H16/L16 -> 41.861711 | Q16: =F16/M16 -> 56.286296
B17: =Data!C12 -> Ipca Labs. | D17: =Data!D12 -> 830.4 | E17: =Data!E12 -> 25.37 | F17: =D17*E17 -> 21067.248 | G17: =Data!I12 -> 93.04 | H17: =F17+G17 -> 21160.288 | K17: =Data!K12 -> 6021.79 | L17: =Data!L12 -> 782.83 | M17: =Data!M12 -> 532.83 | O17: =$H17/K17 -> 3.5139532 | P17: =$H17/L17 -> 27.030502 | Q17: =F17/M17 -> 39.538404
B19: High | O19: =MAX(O8:O17) -> 8.3723422 | P19: =MAX(P8:P17) -> 41.861711 | Q19: =MAX(Q8:Q17) -> 64.127004
B20: 75th Percentile | O20: =QUARTILE(O8:O17,3) -> 5.1779885 | P20: =QUARTILE(P8:P17,3) -> 26.960022 | Q20: =QUARTILE(Q8:Q17,3) -> 54.8557
B21: Average | O21: =AVERAGE(O8:O17) -> 4.1275836 | P21: =AVERAGE(P8:P17) -> 23.726465 | Q21: =AVERAGE(Q8:Q17) -> 39.276479
B22: Median | O22: =MEDIAN(O8:O17) -> 3.3842602 | P22: =MEDIAN(P8:P17) -> 24.751237 | Q22: =MEDIAN(Q8:Q17) -> 39.214451
B23: 25th Percentile | O23: =QUARTILE(O8:O17,1) -> 3.1435521 | P23: =QUARTILE(P8:P17,1) -> 18.491452 | Q23: =QUARTILE(Q8:Q17,1) -> 23.874478
B24: Low | O24: =MIN(O8:O17) -> 1.3088204 | P24: =MIN(P8:P17) -> 11.898354 | Q24: =MIN(Q8:Q17) -> 15.692231
B26: Cipla Company Valuation | O26: EV/Revenue | P26: EV/EBITDA | Q26: P/E
B28: Implied Enterprise Value | O28: =O$22*K8 -> 75381.519 | P28: =P$22*L8 -> 93723.283 | Q28: =Q30+Q29 -> 104315.48
B29: Net Debt | O29: =G8 -> -860.82 | P29: =O29 -> -860.82 | Q29: =P29 -> -860.82
B30: Implied Market Value | O30: =O28-O29 -> 76242.339 | P30: =P28-P29 -> 94584.103 | Q30: =Q22*M8 -> 105176.3
B31: Shares Outstanding | O31: =$E$8 -> 80.72 | P31: =$E$8 -> 80.72 | Q31: =$E$8 -> 80.72
B32: Implied Value per Share | O32: =O30/O31 -> 944.52849 | P32: =P30/P31 -> 1171.7555 | Q32: =Q30/Q31 -> 1302.9769
O34: =IF(O32>$D$8,"Undervalue","Overvalue") -> Undervalue | P34: =IF(P32>$D$8,"Undervalue","Overvalue") -> Undervalue | Q34: =IF(Q32>$D$8,"Undervalue","Overvalue") -> Undervalue

Sheet Data
B2: S.No. | C2: Name | D2: CMP Rs. | E2: No. Eq. Shares Cr. | F2: Market Cap | G2: Debt Rs.Cr. | H2: Cash End Rs.Cr. | I2: Net Debt | J2: EV | K2: Sales Rs.Cr. | L2: EBITDA | M2: NP 12M Rs.Cr.
B3: 1 | C3: Sun Pharma.Inds. | D3: 1012.1 | E3: 239.93 | F3: 242833.15 | G3: 4365.53 | H3: 5033.35 | I3: -667.82 | J3: 242165.33 | K3: 42401.77 | L3: 9328.39 | M3: 4302.66
B4: 2 | C4: Dr Reddy's Labs | D4: 4699.4 | E4: 16.65 | F4: 78245.01 | G4: 1728.9 | H4: 2419.2 | I4: -690.3 | J4: 77554.71 | K4: 23829.5 | L4: 5004.2 | M4: 3644.1
B5: 3 | C5: Cipla | D5: 893.35 | E5: 80.72 | F5: 72111.21 | G5: 1067.66 | H5: 1928.48 | I5: -860.82 | J5: 71250.39 | K5: 22274.15 | L5: 3786.61 | M5: 2682.08
B6: 4 | C6: Torrent Pharma. | D6: 1574.75 | E6: 33.84 | F6: 53289.54 | G6: 4083 | H6: 403.41 | I6: 3679.59 | J6: 56969.13 | K6: 9260 | L6: 2129.8 | M6: 831
B7: 5 | C7: Zydus Lifesci. | D7: 494.15 | E7: 101.22 | F7: 50017.86 | G7: 2446 | H7: 1106.9 | I7: 1339.1 | J7: 51356.96 | K7: 16433.5 | L7: 2793.7 | M7: 2187
B8: 6 | C8: Alkem Lab | D8: 3405.65 | E8: 11.96 | F8: 40731.57 | G8: 1854.59 | H8: 2578.58 | I8: -723.99 | J8: 40007.58 | K8: 11180.52 | L8: 1453.47 | M8: 1047.34
B9: 7 | C9: Aurobindo Pharma | D9: 535.1 | E9: 58.59 | F9: 31351.51 | G9: 4501.21 | H9: 4190.01 | I9: 311.2 | J9: 31662.71 | K9: 24191.79 | L9: 2661.1 | M9: 1997.9
B10: 8 | C10: Biocon | D10: 215.8 | E10: 120.06 | F10: 25908.95 | G10: 5859.4 | H10: 1747.5 | I10: 4111.9 | J10: 30020.85 | K10: 9809.1 | L10: 1275.18 | M10: 512.4
B11: 9 | C11: Syngene Intl. | D11: 604.65 | E11: 40.14 | F11: 24270.65 | G11: 1009 | H11: 515.1 | I11: 493.9 | J11: 24764.55 | K11: 2957.9 | L11: 591.58 | M11: 431.2
B12: 10 | C12: Ipca Labs. | D12: 830.4 | E12: 25.37 | F12: 21067.25 | G12: 733.7 | H12: 640.66 | I12: 93.04 | J12: 21160.29 | K12: 6021.79 | L12: 782.83 | M12: 532.83
